luigi.cpython-37m-x86_64-linux-gnu.so
luigi_engine-0.1.2.dist-info/LICENSE
luigi_engine-0.1.2.dist-info/METADATA
luigi_engine-0.1.2.dist-info/WHEEL
luigi_engine-0.1.2.dist-info/top_level.txt
luigi_engine-0.1.2.dist-info/RECORD
