Metadata-Version: 2.1
Name: luigi-engine
Version: 0.1.2
Summary: Luigi 2D game engine
Home-page: https://github.com/Cc618/Luigi
Author: Cc618
Author-email: celian.dev@gmail.com
License: UNKNOWN
Platform: UNKNOWN
Classifier: Development Status :: 4 - Beta
Classifier: License :: OSI Approved :: MIT License
Classifier: Programming Language :: Python :: 3
Classifier: Programming Language :: C++
Classifier: Topic :: Games/Entertainment
